plutoid/__init__.py
plutoid/executor.py
plutoid/matplotlib_backend.py
plutoid/monitor.py
plutoid/stream.py
plutoid-0.1.2.dist-info/DESCRIPTION.rst
plutoid-0.1.2.dist-info/METADATA
plutoid-0.1.2.dist-info/RECORD
plutoid-0.1.2.dist-info/WHEEL
plutoid-0.1.2.dist-info/metadata.json
plutoid-0.1.2.dist-info/top_level.txt
