Metadata-Version: 2.0
Name: plutoid
Version: 0.1.2
Summary: A light weight Python kernel
Home-page: https://github.com/manasgarg/plutoid
Author: Manas Garg
Author-email: manasgarg@gmail.com
License: MIT
Platform: UNKNOWN
